statsd-echo-server/__init__.py
statsd-echo-server/statsd_echo_server.py
statsd_echo_server/__init__.py
statsd_echo_server/__main__.py
statsd_logger/__init__.py
statsd_logger/__main__.py
statsd_logger-0.2.1.dist-info/METADATA
statsd_logger-0.2.1.dist-info/RECORD
statsd_logger-0.2.1.dist-info/WHEEL
statsd_logger-0.2.1.dist-info/entry_points.txt
statsd_logger-0.2.1.dist-info/top_level.txt
