Metadata-Version: 2.1
Name: statsd-logger
Version: 0.2.1
Summary: Simple StatsD Echo Server
Home-page: https://gitlab.com/kpgadkari/statsd-echo-server
Author: Kaustubh Gadkari
Author-email: kaustubh.gadkari@gmail.com
License: License :: OSI Approved :: GNU General Public License v3 (GPLv3)
Platform: UNKNOWN
Classifier: Programming Language :: Python :: 3
Classifier: License :: OSI Approved :: GNU General Public License v3 (GPLv3)
Requires-Python: >=3.0.0, >=2.7.0
Requires-Dist: termcolor
